simqcore/__init__.py
simqcore/asyncio.py
simqcore/base.py
simqcore-0.2.3.dist-info/LICENSE
simqcore-0.2.3.dist-info/METADATA
simqcore-0.2.3.dist-info/WHEEL
simqcore-0.2.3.dist-info/top_level.txt
simqcore-0.2.3.dist-info/RECORD
